guwencombo/__init__.py
guwencombo/guwencombo.py
guwencombo/download/filesize.txt
guwencombo-1.6.2.dist-info/LICENSE.txt
guwencombo-1.6.2.dist-info/METADATA
guwencombo-1.6.2.dist-info/WHEEL
guwencombo-1.6.2.dist-info/top_level.txt
guwencombo-1.6.2.dist-info/RECORD
