Metadata-Version: 2.1
Name: guwencombo
Version: 1.6.2
Summary: Tokenizer POS-tagger and Dependency-parser for Classical Chinese
Home-page: https://github.com/KoichiYasuoka/GuwenCOMBO
Author: Koichi Yasuoka
Author-email: yasuoka@kanji.zinbun.kyoto-u.ac.jp
License: GPL
Project-URL: COMBO-pytorch, https://gitlab.clarin-pl.eu/syntactic-tools/combo
Project-URL: Source, https://github.com/KoichiYasuoka/GuwenCOMBO
Project-URL: Tracker, https://github.com/KoichiYasuoka/GuwenCOMBO/issues
Keywords: NLP Chinese
Classifier: License :: OSI Approved :: GNU General Public License (GPL)
Classifier: Programming Language :: Python :: 3
Classifier: Operating System :: OS Independent
Classifier: Topic :: Text Processing :: Linguistic
Requires-Python: >=3.6
License-File: LICENSE.txt
Requires-Dist: udkundoku (>=2.3.0)
Requires-Dist: unidic-combo (>=1.5.4)
